demos/__init__.py
demos/simple_demo/__init__.py
demos/simple_demo/config.py
demos/simple_demo/jiandan_spider.py
yy_spider/__init__.py
yy_spider/run_server.py
yy_spider/run_spider.py
yy_spider/client/__init__.py
yy_spider/client/spiders/__init__.py
yy_spider/client/spiders/base_spider.py
yy_spider/common/__init__.py
yy_spider/common/yy_exceptions.py
yy_spider/database/__init__.py
yy_spider/database/db_handler.py
yy_spider/message_bus/__init__.py
yy_spider/message_bus/base_bus.py
yy_spider/message_bus/common.py
yy_spider/message_bus/socket_bus.py
yy_spider/server/__init__.py
yy_spider/server/server.py
yy_spider/settings/__init__.py
yy_spider/settings/default_settings.py
yy_spider/utils/__init__.py
yy_spider/utils/yy_logger.py
yy_spider-1.0.0.dist-info/DESCRIPTION.rst
yy_spider-1.0.0.dist-info/METADATA
yy_spider-1.0.0.dist-info/RECORD
yy_spider-1.0.0.dist-info/WHEEL
yy_spider-1.0.0.dist-info/entry_points.txt
yy_spider-1.0.0.dist-info/metadata.json
yy_spider-1.0.0.dist-info/top_level.txt
