Metadata-Version: 2.0
Name: yy-spider
Version: 1.0.0
Summary: 一个增量式爬虫系统
Home-page: https://github.com/yy-spider/yy_spider
Author: xsren
Author-email: bestrenxs@gmail.com
License: BSD
Keywords: spider increment distribute
Platform: UNKNOWN
Classifier: Framework :: Scrapy
Classifier: Development Status :: 5 - Production/Stable
Classifier: Environment :: Console
Classifier: Intended Audience :: Developers
Classifier: License :: OSI Approved :: BSD License
Classifier: Operating System :: OS Independent
Classifier: Programming Language :: Python :: 3
Classifier: Programming Language :: Python :: 3.3
Classifier: Programming Language :: Python :: 3.4
Classifier: Programming Language :: Python :: 3.5
Classifier: Programming Language :: Python :: 3.6
Classifier: Topic :: Internet :: WWW/HTTP
Classifier: Topic :: Software Development :: Libraries :: Application Frameworks
Classifier: Topic :: Software Development :: Libraries :: Python Modules
Requires-Dist: Automat (==0.6.0)
Requires-Dist: Twisted (==17.9.0)
Requires-Dist: attrs (==17.3.0)
Requires-Dist: certifi (==2017.11.5)
Requires-Dist: chardet (==3.0.4)
Requires-Dist: constantly (==15.1.0)
Requires-Dist: gevent (==1.2.2)
Requires-Dist: greenlet (==0.4.12)
Requires-Dist: hyperlink (==17.3.1)
Requires-Dist: idna (==2.6)
Requires-Dist: incremental (==17.5.0)
Requires-Dist: lxml (==4.1.1)
Requires-Dist: msgpack (==0.5.0)
Requires-Dist: pymongo (==3.6.0)
Requires-Dist: requests (==2.18.4)
Requires-Dist: six (==1.11.0)
Requires-Dist: urllib3 (==1.22)
Requires-Dist: zope.interface (==4.4.3)
